{
    "case_index": 43,
    "nhs": "unknown",
    "resolved_facts": {
        "Baseline CT: Detail incidental finding(h)": "",
        "Chemotherapy: Dates": "Cancer Target Dates",
        "Demographics: \nNHS number(d)": "NHS Number: \nName: Freya Kind\nGender: Female\nDOB: 06/05/1971   Age: 55 Years",
        "Histology: Biopsy result(g)": "Staging & Diagnosis(g)",
        "Histology: Biopsy date(g)": "Staging & Diagnosis(g)",
        "Demographics:\nPrevious cancer \n(y, n) \nif yes, where(f)": "Rectal adenocarcinoma\nICD10 Code: D12.8\nDifferentiation: Poorly differentiated",
        "Demographics: \nState site of previous cancer(f)": "Integrated TNM Stage: \nDukes:",
        "Baseline CT: Incidental findings requiring follow up? Y/N(h)": "CT: fullness at low rectum, no distant disease.",
        "MDT (after 12 week): Decision ": "MDT Outcome(h)",
        "MDT (after 12 week): Date": "MDT Outcome(h)",
        "2nd MRI: Patient pathway status": "For MRI rectum and colonoscopy",
        "2nd MRI: Date": "For MRI rectum and colonoscopy"
    }
}